rasa_vier_cvg/__init__.py
rasa_vier_cvg/cvg.py
rasa_vier_cvg-1.4.0.dist-info/LICENSE
rasa_vier_cvg-1.4.0.dist-info/METADATA
rasa_vier_cvg-1.4.0.dist-info/WHEEL
rasa_vier_cvg-1.4.0.dist-info/top_level.txt
rasa_vier_cvg-1.4.0.dist-info/RECORD
