Metadata-Version: 2.1
Name: rasa-vier-cvg
Version: 1.4.0
Summary: Rasa-integration for the VIER Cognitive Voice Gateway
Home-page: https://cognitivevoice.io
Author: VIER GmbH
Author-email: support@vier.ai
License: MIT
Project-URL: Source, https://github.com/VIER-CognitiveVoice/rasa-vier-cvg
Project-URL: Bug Reports, https://github.com/VIER-CognitiveVoice/rasa-vier-cvg/issues
Keywords: VIER,VIER Cognitive Voice Gateway SDK,Channel
Requires-Python: >=3.6
License-File: LICENSE
Requires-Dist: aiodns
Requires-Dist: aiohttp
Requires-Dist: asyncio
Requires-Dist: rasa-sdk
